dll_injector/__init__.py
dll_injector/dll_injector.py
dll_injector/libs/dll_injector.dll
DLL_Injector-1.0.5.dist-info/LICENSE
DLL_Injector-1.0.5.dist-info/METADATA
DLL_Injector-1.0.5.dist-info/WHEEL
DLL_Injector-1.0.5.dist-info/top_level.txt
DLL_Injector-1.0.5.dist-info/RECORD
