Metadata-Version: 2.1
Name: DLL-Injector
Version: 1.0.5
Summary: DLL-Injector is a library for injecting DLLs into processes using Python.
Home-page: https://github.com/LixNew2/DLL-Injector
Author: LixNew
Author-email: lixnew2@gmail.com
Classifier: Programming Language :: Python :: 3
Classifier: License :: OSI Approved :: MIT License
Classifier: Operating System :: OS Independent
Requires-Python: >=3.6
License-File: LICENSE
Requires-Dist: psutil
